jack_mcp_server/__init__.py
jack_mcp_server-0.1.1.dist-info/WHEEL
jack_mcp_server-0.1.1.dist-info/entry_points.txt
jack_mcp_server-0.1.1.dist-info/METADATA
jack_mcp_server-0.1.1.dist-info/RECORD
