Metadata-Version: 2.3
Name: jack-mcp-server
Version: 0.1.1
Summary: Add your description here
Author: fu123
Author-email: fu123 <fuqw92@126.com>
Requires-Dist: map[cli]>=1.3.0
Requires-Python: >=3.13
